{
	"width": 10,
	"height": 30,
	"jumpSpeed": 110,
	"maxJumpTime": 1,
	"jumpGravityMultiplier": 0.45,
	"acceleration": 400,
	"deceleration": 500,
	"airAcceleration": 100,
	"maxWalkSpeed": 150,
	"maxFallSpeed": 400,
	"walkCycleTime": 1,
	"dontChangeDirectionInAir": true,
	"fallPoseSpeed": 100,
	"skidSpeed": 25,
	"skidWhenTryingToStop": false,
	"picksUp": true,
	"dontChangeDirectionWhileSkidding": true,
	"jumpDamage" : 1,
	"maximumBounceJumpSpeed": 200,
	"bounceJumpSpeedMultiplier" : 1.5,
	"maxBounceJumpTime" : 1
}
